integracaoTracker/__init__.py
integracaoTracker/module_integracao.py
integracaoTracker/utils.py
utilFunctions/__init__.py
utilFunctions/config.py
utilFunctions/module.py
utilFunctions/data/fretes.db
utilFunctions/data/shapesMiniAnel.shp
pacofunctions-0.0.8.dist-info/METADATA
pacofunctions-0.0.8.dist-info/WHEEL
pacofunctions-0.0.8.dist-info/top_level.txt
pacofunctions-0.0.8.dist-info/RECORD
